configya/__init__.py
configya/_version.py
configya/file_utils.py
configya/yaml_config.py
configya-1.0.0.dist-info/LICENSE
configya-1.0.0.dist-info/METADATA
configya-1.0.0.dist-info/WHEEL
configya-1.0.0.dist-info/top_level.txt
configya-1.0.0.dist-info/RECORD
