Metadata-Version: 2.1
Name: configya
Version: 1.0.0
Summary: A generic YAML config file generator
Home-page: https://github.com/grburgess/configya
Author: J. Michael Burgess
Author-email: jmichaelburgess@gmail.com
License: GPL-3+
Project-URL: Bug Tracker, https://github.com/grburgess/configya/issues
Project-URL: Source Code, https://github.com/grburgess/configya
Platform: UNKNOWN
Classifier: Development Status :: 2 - Pre-Alpha
Classifier: Environment :: Console
Classifier: Intended Audience :: Science/Research
Classifier: License :: OSI Approved :: GNU General Public License v3 or later (GPLv3+)
Classifier: Operating System :: POSIX
Classifier: Programming Language :: Python :: 3.5
Classifier: Programming Language :: Python :: 3.6
Classifier: Programming Language :: Python :: 3.7
Classifier: Programming Language :: Python :: 3.8
Requires-Dist: pyyaml
Requires-Dist: nested-diff
